btc_com/__init__.py
btc_com/explorer.py
btc_com/util.py
explorer/__init__.py
explorer/explorer.py
explorer/util.py
btc_com-0.0.1.dist-info/LICENSE
btc_com-0.0.1.dist-info/METADATA
btc_com-0.0.1.dist-info/WHEEL
btc_com-0.0.1.dist-info/top_level.txt
btc_com-0.0.1.dist-info/RECORD
