Metadata-Version: 2.1
Name: btc-com
Version: 0.0.1
Summary: An api wrapper for btc.com block explorer api
Home-page: https://github.com/pasquantonio/
Author: Joe Pasquantonio
Author-email: joepasquantonio@gmail.com
License: UNKNOWN
Platform: UNKNOWN
Classifier: Programming Language :: Python :: 3
Classifier: License :: OSI Approved :: MIT License
Classifier: Operating System :: OS Independent
Requires-Python: >=3
Requires-Dist: requests
